nextsong/__init__.py
nextsong/__main__.py
nextsong/cli.py
nextsong/config/__init__.py
nextsong/config/_config.py
nextsong/datatypes/__init__.py
nextsong/datatypes/_datatypes.py
nextsong/playlist/__init__.py
nextsong/playlist/_playlist.py
nextsong/sample/__init__.py
nextsong/sample/_sample.py
nextsong/sequence/__init__.py
nextsong/sequence/_sequence.py
nextsong-1.2.1.dist-info/LICENSE
nextsong-1.2.1.dist-info/METADATA
nextsong-1.2.1.dist-info/WHEEL
nextsong-1.2.1.dist-info/entry_points.txt
nextsong-1.2.1.dist-info/top_level.txt
nextsong-1.2.1.dist-info/RECORD
