Metadata-Version: 2.1
Name: nextsong
Version: 1.2.1
Summary: A media playlist library for Python
Home-page: https://gitlab.com/samflam/nextsong
Author: samflam
Author-email: nextsong@samflam.com
License: UNKNOWN
Platform: UNKNOWN
Classifier: Programming Language :: Python :: 3
Classifier: License :: OSI Approved :: MIT License
Classifier: Operating System :: POSIX :: Linux
Requires-Python: >=3.7
License-File: LICENSE
Requires-Dist: lxml (>=4)
